monitor/__init__.py
monitor/lib/__init__.py
monitor/lib/config.py
monitor/lib/daemon.py
monitor/lib/database.py
monitor/lib/exceptions.py
monitor/lib/executor.py
monitor/lib/metrics.py
monitor/lib/result.py
monitor/lib/utils.py
tests/__init__.py
PyMonitorLib-0.3.0.dist-info/LICENSE
PyMonitorLib-0.3.0.dist-info/METADATA
PyMonitorLib-0.3.0.dist-info/WHEEL
PyMonitorLib-0.3.0.dist-info/top_level.txt
PyMonitorLib-0.3.0.dist-info/RECORD
