Metadata-Version: 2.1
Name: PyMonitorLib
Version: 0.3.0
Summary: Library for creating simple interval processes. This is especially useful for interval based monitoring application that generate telemetry at a set interval.
Home-page: https://github.com/Aprelius/PyMonitorLib
Author: Daniel Weiner
Author-email: info@phantomnet.net
License: UNKNOWN
Platform: UNKNOWN
Classifier: Development Status :: 3 - Alpha
Classifier: Programming Language :: Python :: 3
Classifier: License :: OSI Approved :: MIT License
Classifier: Operating System :: OS Independent
Requires-Python: >=3.6
